esopipeline/__init__.py
esopipeline/__main__.py
esopipeline/datalog.py
esopipeline/sofd.py
esopipeline/table.py
esopipeline/workflow.py
esopipeline/io/__init__.py
esopipeline/io/fitsutils.py
esopipeline/io/templates.py
esopipeline/templates/gravity/gravity_categories.dat
esopipeline/templates/gravity/gravity_keywords.dat
esopipeline/templates/gravity/default/sofd_gravity_default_dark.dat
esopipeline/templates/gravity/default/sofd_gravity_default_mergetf.dat
esopipeline/templates/gravity/default/sofd_gravity_default_mergevis.dat
esopipeline/templates/gravity/default/sofd_gravity_default_p2vm.dat
esopipeline/templates/gravity/default/sofd_gravity_default_vis.dat
esopipeline/templates/gravity/default/sofd_gravity_default_viscal.dat
esopipeline/templates/gravity/default/workflow_gravity_default.dat
esopipeline/templates/gravity/dispersion/sofd_gravity_disp_dark.dat
esopipeline/templates/gravity/dispersion/sofd_gravity_disp_disp.dat
esopipeline/templates/gravity/dispersion/sofd_gravity_disp_p2vm.dat
esopipeline/templates/gravity/dispersion/sofd_gravity_disp_wavelamp.dat
esopipeline/templates/gravity/dispersion/workflow_gravity_dispersion.dat
testing/__init__.py
testing/datalog.py
testing/esorex.py
testing/pipeline.py
testing/workflow.py
esopipeline-0.1.dist-info/LICENSE.txt
esopipeline-0.1.dist-info/METADATA
esopipeline-0.1.dist-info/WHEEL
esopipeline-0.1.dist-info/entry_points.txt
esopipeline-0.1.dist-info/top_level.txt
esopipeline-0.1.dist-info/RECORD
