Metadata-Version: 2.1
Name: esopipeline
Version: 0.1
Summary: Process astronomical data from European Southern Observatory
Home-page: UNKNOWN
Author: Régis Lachaume
Author-email: regis.lachaume@gmail.com
License: LICENSE.txt
Platform: UNKNOWN
Classifier: Programming Language :: Python :: 3
Classifier: Development Status :: 3 - Alpha 
Classifier: Operating System :: OS Independent
Classifier: Intended Audience :: Science/Research
Classifier: Topic :: Scientific/Engineering :: Astronomy
Classifier: License :: Public Domain
Requires-Python: >=3.8
Requires-Dist: astropy
Requires-Dist: numpy
Requires-Dist: pyoifits
